up_purple.py
up_purple-0.1.5.dist-info/LICENSE.txt
up_purple-0.1.5.dist-info/METADATA
up_purple-0.1.5.dist-info/WHEEL
up_purple-0.1.5.dist-info/top_level.txt
up_purple-0.1.5.dist-info/RECORD
