Metadata-Version: 2.1
Name: up-purple
Version: 0.1.5
Summary: PURPLE Integration with the UP
Home-page: https://www.black-sat.org
Author: Nicola Gigante
Author-email: nicola.gigante@unibz.it
License: MIT
Platform: UNKNOWN
Classifier: License :: OSI Approved :: MIT License
Classifier: Topic :: Scientific/Engineering :: Artificial Intelligence
Requires-Dist: black-sat
Requires-Dist: purple-plan
Requires-Dist: unified-planning
